{"images":[{"filename":"[37]_[Front]_[Screen01]_[Ama01] 077.jpg","width":1080,"height":1920}],"annotations":[{"attributes":[],"class":"keypoint_club","points":[297,615,1,0,0,0,0,0,0]},{"box":[265,400,397,1042],"attributes":[],"class":"0"},{"box":[538,362,65,28],"attributes":[],"class":"6"},{"box":[271,599,44,52],"attributes":[],"class":"2"},{"box":[308,579,45,46],"attributes":[],"class":"2"},{"box":[297,1323,98,94],"attributes":[],"class":"3"},{"box":[568,1342,90,92],"attributes":[],"class":"3"},{"box":[459,1566,50,55],"attributes":[],"class":"5"},{"box":[442,401,159,227],"attributes":[],"class":"1"},{"attributes":[],"class":"0","points":[506,568,2,483,537,2,534,547,2]}]}