{"images":[{"filename":"[37]_[Side]_[Screen01]_[Ama01] 137.jpg","width":1080,"height":1920}],"annotations":[{"attributes":[],"class":"keypoint_club","points":[649,1162,1,795,1366,2,764,1358,2]},{"box":[822,1477,22,25],"attributes":[],"class":"5"},{"box":[631,1144,36,44],"attributes":[],"class":"2"},{"box":[636,1118,37,51],"attributes":[],"class":"2"},{"box":[484,1438,133,58],"attributes":[],"class":"3"},{"box":[479,1477,149,66],"attributes":[],"class":"3"},{"box":[612,878,114,111],"attributes":[],"class":"1"},{"box":[451,874,274,670],"attributes":[],"class":"0"},{"box":[760,1312,64,112],"attributes":[],"class":"6"},{"attributes":[],"class":"0","points":[679,977,2,682,961,2,680,963,1]}]}