{"images":[{"filename":"[22]_[Side]_[Screen01]_[Ama01] 185.jpg","width":1080,"height":1920}],"annotations":[{"attributes":[],"class":"keypoint_club","points":[390,880,1,0,0,0,0,0,0]},{"box":[364,818,216,736],"attributes":[],"class":"0"},{"box":[368,862,58,43],"attributes":[],"class":"2"},{"box":[611,1028,56,54],"attributes":[],"class":"6"},{"box":[479,823,99,105],"attributes":[],"class":"1"},{"box":[409,1446,111,43],"attributes":[],"class":"3"},{"box":[428,1457,97,96],"attributes":[],"class":"3"},{"attributes":[],"class":"0","points":[517,863,1,531,853,1,508,848,1]}]}