{"images":[{"filename":"[46]_[Front]_[Screen01]_[Ama01] 105.jpg","width":1080,"height":1920}],"annotations":[{"attributes":[],"class":"keypoint_club","points":[378,523,1,879,624,2,885,571,2]},{"box":[283,374,359,1054],"attributes":[],"class":"0"},{"box":[417,376,175,225],"attributes":[],"class":"1"},{"box":[372,499,46,59],"attributes":[],"class":"2"},{"box":[400,491,40,59],"attributes":[],"class":"2"},{"box":[870,567,45,70],"attributes":[],"class":"6"},{"box":[550,1327,95,101],"attributes":[],"class":"3"},{"box":[279,1300,114,131],"attributes":[],"class":"3"},{"box":[449,1565,51,47],"attributes":[],"class":"5"},{"attributes":[],"class":"0","points":[472,548,2,460,521,2,492,527,2]}]}