{"images":[{"filename":"[43]_[Side]_[Screen01]_[Ama01] 181.jpg","width":1080,"height":1920}],"annotations":[{"attributes":[],"class":"keypoint_club","points":[398,885,1,0,0,0,0,0,0]},{"box":[369,817,197,728],"attributes":[],"class":"0"},{"box":[462,818,103,86],"attributes":[],"class":"1"},{"box":[407,864,38,39],"attributes":[],"class":"2"},{"box":[385,870,26,34],"attributes":[],"class":"2"},{"box":[414,1445,114,97],"attributes":[],"class":"3"},{"box":[406,1444,117,41],"attributes":[],"class":"3"},{"box":[624,1270,7,8],"attributes":[],"class":"5"},{"attributes":[],"class":"0","points":[559,897,1,578,888,1,557,878,1]}]}