{"images":[{"filename":"[25]_[Side]_[Screen01]_[Ama01] 005.jpg","width":1080,"height":1920}],"annotations":[{"attributes":[],"class":"keypoint_club","points":[578,1183,2,849,1487,2,819,1501,2]},{"box":[416,886,290,652],"attributes":[],"class":"0"},{"box":[584,1190,49,55],"attributes":[],"class":"2"},{"box":[611,887,91,108],"attributes":[],"class":"1"},{"box":[816,1479,40,26],"attributes":[],"class":"6"},{"box":[823,1477,16,17],"attributes":[],"class":"5"},{"box":[493,1451,110,31],"attributes":[],"class":"3"},{"box":[472,1483,133,51],"attributes":[],"class":"3"},{"attributes":[],"class":"0","points":[659,990,2,660,967,2,666,966,1]}]}