{"images":[{"filename":"[28]_[Front]_[Screen01]_[Ama01] 209.jpg","width":1080,"height":1920}],"annotations":[{"box":[231,342,450,1086],"attributes":[],"class":"0"},{"box":[311,607,53,78],"attributes":[],"class":"6"},{"box":[444,524,29,20],"attributes":[],"class":"2"},{"box":[230,1297,135,131],"attributes":[],"class":"3"},{"box":[574,1324,104,99],"attributes":[],"class":"3"},{"box":[485,341,166,157],"attributes":[],"class":"1"},{"attributes":[],"class":"0","points":[628,471,2,623,455,2,623,459,1]}]}