{"images":[{"filename":"[31]_[Front]_[Screen01]_[Ama01] 141.jpg","width":1080,"height":1920}],"annotations":[{"attributes":[],"class":"keypoint_club","points":[0,0,0,0,0,0,0,0,0]},{"box":[245,480,340,907],"attributes":[],"class":"0"},{"box":[376,487,143,170],"attributes":[],"class":"1"},{"box":[252,625,46,45],"attributes":[],"class":"2"},{"box":[296,616,45,43],"attributes":[],"class":"2"},{"box":[246,1286,104,86],"attributes":[],"class":"3"},{"box":[509,1297,68,86],"attributes":[],"class":"3"},{"box":[460,1568,49,47],"attributes":[],"class":"5"},{"box":[707,442,65,71],"attributes":[],"class":"6"},{"attributes":[],"class":"0","points":[427,605,2,416,586,2,449,590,2]}]}