{"images":[{"filename":"[43]_[Front]_[Screen01]_[Ama01] 081.jpg","width":1080,"height":1920}],"annotations":[{"attributes":[],"class":"keypoint_club","points":[313,664,2,723,486,2,681,489,2]},{"box":[453,1556,66,60],"attributes":[],"class":"5"},{"box":[279,1276,86,86],"attributes":[],"class":"3"},{"box":[536,1296,75,83],"attributes":[],"class":"3"},{"box":[302,616,60,49],"attributes":[],"class":"2"},{"box":[339,602,66,60],"attributes":[],"class":"2"},{"box":[422,470,137,180],"attributes":[],"class":"1"},{"box":[279,465,334,925],"attributes":[],"class":"0"},{"attributes":[],"class":"0","points":[470,603,2,458,582,2,489,590,2]}]}