{"images":[{"filename":"[28]_[Side]_[Screen01]_[Ama01] 081.jpg","width":1080,"height":1920}],"annotations":[{"attributes":[],"class":"keypoint_club","points":[0,0,0,0,0,0,0,0,0]},{"box":[429,867,297,672],"attributes":[],"class":"0"},{"box":[606,888,115,112],"attributes":[],"class":"1"},{"box":[526,872,40,48],"attributes":[],"class":"2"},{"box":[511,872,28,39],"attributes":[],"class":"2"},{"box":[487,1473,131,63],"attributes":[],"class":"3"},{"box":[534,1452,71,30],"attributes":[],"class":"3"},{"box":[812,1478,21,22],"attributes":[],"class":"5"},{"attributes":[],"class":"0","points":[677,989,2,684,983,1,677,975,2]}]}