{"images":[{"filename":"[37]_[Side]_[Screen01]_[Ama01] 145.jpg","width":1080,"height":1920}],"annotations":[{"attributes":[],"class":"keypoint_club","points":[606,1124,1,779,1390,2,743,1380,2]},{"box":[461,869,268,674],"attributes":[],"class":"0"},{"box":[488,1466,140,75],"attributes":[],"class":"3"},{"box":[488,1444,122,44],"attributes":[],"class":"3"},{"box":[619,869,109,118],"attributes":[],"class":"1"},{"box":[608,1157,39,30],"attributes":[],"class":"2"},{"attributes":[],"class":"0","points":[677,970,2,682,961,2,680,963,1]}]}