{"images":[{"filename":"[37]_[Side]_[Screen01]_[Ama01] 125.jpg","width":1080,"height":1920}],"annotations":[{"attributes":[],"class":"keypoint_club","points":[0,0,0,0,0,0,0,0,0]},{"box":[822,1480,21,23],"attributes":[],"class":"5"},{"box":[441,890,292,646],"attributes":[],"class":"0"},{"box":[567,950,46,62],"attributes":[],"class":"2"},{"box":[548,924,36,50],"attributes":[],"class":"2"},{"box":[469,703,34,18],"attributes":[],"class":"6"},{"box":[487,1469,140,65],"attributes":[],"class":"3"},{"box":[545,1450,67,37],"attributes":[],"class":"3"},{"box":[629,890,101,110],"attributes":[],"class":"1"},{"attributes":[],"class":"0","points":[687,980,2,691,968,2,687,970,1]}]}