{"images":[{"filename":"[16]_[Front]_[Screen01]_[Ama01] 141.jpg","width":1080,"height":1920}],"annotations":[{"attributes":[],"class":"keypoint_club","points":[317,862,1,0,0,0,0,0,0]},{"box":[254,409,408,1017],"attributes":[],"class":"0"},{"box":[441,409,160,226],"attributes":[],"class":"1"},{"box":[253,823,66,72],"attributes":[],"class":"2"},{"box":[303,823,105,78],"attributes":[],"class":"2"},{"box":[442,1559,47,55],"attributes":[],"class":"5"},{"box":[290,1337,106,74],"attributes":[],"class":"3"},{"box":[575,1345,83,81],"attributes":[],"class":"3"},{"attributes":[],"class":"0","points":[508,574,2,491,553,2,525,555,2]}]}