{"images":[{"filename":"[28]_[Side]_[Screen01]_[Ama01] 029.jpg","width":1080,"height":1920}],"annotations":[{"attributes":[],"class":"keypoint_club","points":[589,1188,2,874,1491,2,837,1512,2]},{"box":[423,902,288,631],"attributes":[],"class":"0"},{"box":[620,901,87,107],"attributes":[],"class":"1"},{"box":[597,1195,41,47],"attributes":[],"class":"2"},{"box":[483,1479,139,57],"attributes":[],"class":"3"},{"box":[534,1443,67,36],"attributes":[],"class":"3"},{"box":[836,1483,41,30],"attributes":[],"class":"6"},{"box":[809,1480,22,19],"attributes":[],"class":"5"},{"attributes":[],"class":"0","points":[672,989,2,0,0,0,673,989,1]}]}