{"images":[{"filename":"[22]_[Front]_[Screen01]_[Ama01] 021.jpg","width":1080,"height":1920}],"annotations":[{"attributes":[],"class":"keypoint_club","points":[456,972,1,208,1640,2,261,1591,2]},{"box":[257,467,337,918],"attributes":[],"class":"0"},{"box":[153,1587,109,67],"attributes":[],"class":"6"},{"box":[416,954,52,63],"attributes":[],"class":"2"},{"box":[440,933,53,52],"attributes":[],"class":"2"},{"box":[514,1322,74,63],"attributes":[],"class":"3"},{"box":[258,1313,78,63],"attributes":[],"class":"3"},{"box":[461,1568,45,47],"attributes":[],"class":"5"},{"box":[411,467,150,189],"attributes":[],"class":"1"},{"attributes":[],"class":"0","points":[481,620,2,466,591,2,509,594,2]}]}