{"images":[{"filename":"[16]_[Side]_[Screen01]_[Ama01] 085.jpg","width":1080,"height":1920}],"annotations":[{"attributes":[],"class":"keypoint_club","points":[512,877,1,605,1024,1,623,1003,1]},{"box":[811,1481,22,22],"attributes":[],"class":"5"},{"box":[416,860,289,676],"attributes":[],"class":"0"},{"box":[495,860,45,43],"attributes":[],"class":"2"},{"box":[591,878,111,108],"attributes":[],"class":"1"},{"box":[461,1481,139,53],"attributes":[],"class":"3"},{"box":[518,1450,72,34],"attributes":[],"class":"3"},{"attributes":[],"class":"0","points":[655,973,2,658,959,2,664,965,1]}]}