{"images":[{"filename":"[28]_[Front]_[Screen01]_[Ama01] 009.jpg","width":1080,"height":1920}],"annotations":[{"attributes":[],"class":"keypoint_club","points":[540,963,1,425,1560,2,454,1589,2]},{"box":[297,415,379,1017],"attributes":[],"class":"0"},{"box":[584,1335,76,96],"attributes":[],"class":"3"},{"box":[296,1329,99,95],"attributes":[],"class":"3"},{"box":[471,417,161,214],"attributes":[],"class":"1"},{"box":[424,1559,39,57],"attributes":[],"class":"6"},{"box":[469,1557,48,53],"attributes":[],"class":"5"},{"box":[493,968,49,73],"attributes":[],"class":"2"},{"box":[516,938,64,86],"attributes":[],"class":"2"},{"attributes":[],"class":"0","points":[548,586,2,532,563,2,566,568,2]}]}