{"images":[{"filename":"[25]_[Front]_[Screen01]_[Ama01] 141.jpg","width":1080,"height":1920}],"annotations":[{"attributes":[],"class":"keypoint_club","points":[0,0,0,0,0,0,0,0,0]},{"box":[215,399,444,1037],"attributes":[],"class":"0"},{"box":[450,402,164,226],"attributes":[],"class":"1"},{"box":[230,727,78,70],"attributes":[],"class":"2"},{"box":[221,693,61,59],"attributes":[],"class":"2"},{"box":[295,1321,107,94],"attributes":[],"class":"3"},{"box":[574,1343,81,89],"attributes":[],"class":"3"},{"box":[464,1567,50,53],"attributes":[],"class":"5"},{"box":[86,416,42,23],"attributes":[],"class":"6"},{"attributes":[],"class":"0","points":[509,567,2,491,536,2,541,545,2]}]}