{"images":[{"filename":"[40]_[Side]_[Screen01]_[Ama01] 013.jpg","width":1080,"height":1920}],"annotations":[{"attributes":[],"class":"keypoint_club","points":[721,1203,1,864,1499,2,0,0,0]},{"box":[561,902,284,619],"attributes":[],"class":"0"},{"box":[738,905,104,103],"attributes":[],"class":"1"},{"box":[703,1163,29,39],"attributes":[],"class":"2"},{"box":[716,1202,32,42],"attributes":[],"class":"2"},{"box":[625,1476,126,48],"attributes":[],"class":"3"},{"box":[609,1460,120,35],"attributes":[],"class":"3"},{"box":[827,1493,44,19],"attributes":[],"class":"6"},{"box":[832,1482,14,16],"attributes":[],"class":"5"},{"attributes":[],"class":"0","points":[778,1009,2,794,992,2,794,981,1]}]}