{"images":[{"filename":"[43]_[Front]_[Screen01]_[Ama01] 113.jpg","width":1080,"height":1920}],"annotations":[{"attributes":[],"class":"keypoint_club","points":[391,603,1,904,685,2,888,645,2]},{"box":[869,627,54,71],"attributes":[],"class":"6"},{"box":[463,1558,52,46],"attributes":[],"class":"5"},{"box":[363,570,46,77],"attributes":[],"class":"2"},{"box":[395,590,48,51],"attributes":[],"class":"2"},{"box":[280,1270,92,94],"attributes":[],"class":"3"},{"box":[526,1301,83,74],"attributes":[],"class":"3"},{"box":[417,464,149,180],"attributes":[],"class":"1"},{"box":[272,458,343,923],"attributes":[],"class":"0"},{"attributes":[],"class":"0","points":[471,596,2,461,576,2,489,583,2]}]}